setup.py
pytcga/__init__.py
pytcga/clinical_data_dictionary.py
pytcga/tcga_clinical.py
pytcga/tcga_mutations.py
pytcga/tcga_requests.py
pytcga/tcga_rna.py
pytcga/urls.py
pytcga.egg-info/PKG-INFO
pytcga.egg-info/SOURCES.txt
pytcga.egg-info/dependency_links.txt
pytcga.egg-info/requires.txt
pytcga.egg-info/top_level.txt