Metadata-Version: 1.1
Name: pytcga
Version: 0.0.2
Summary: Store and query public TCGA data
Home-page: https://github.com/arahuja/pytcga
Author: Arun Ahuja
Author-email: aahuja11 {at} gmail {dot}
License: UNKNOWN
Platform: UNKNOWN
Classifier: Development Status :: 3 - Alpha
Classifier: Environment :: Console
Classifier: Operating System :: OS Independent
Classifier: Intended Audience :: Science/Research
Classifier: Programming Language :: Python
Classifier: Topic :: Scientific/Engineering :: Bio-Informatics
